pipebit/__init__.py
pipebit/bitbatchreceiver.py
pipebit/bitbatchsender.py
pipebit/bitflowreceiver.py
pipebit/bitflowsender.py
pipebit/bitpackreceiver.py
pipebit/bitpacksender.py
pipebit/initial_config.py
pipebit_test1-0.0.1.dist-info/METADATA
pipebit_test1-0.0.1.dist-info/WHEEL
pipebit_test1-0.0.1.dist-info/top_level.txt
pipebit_test1-0.0.1.dist-info/RECORD
